src/scheduler.v
module scheduler #(
    parameter integer NUM_FLOOR   = 5,
    parameter integer FLOOR_WIDTH = $clog2(NUM_FLOOR)
)(
    input  wire [FLOOR_WIDTH-1:0] current_floor,
    input  wire                   direction,        // 0 = UP, 1 = DOWN
    input  wire [NUM_FLOOR-1:0]   pending_request,

    output reg  [FLOOR_WIDTH-1:0] target_request,
    output reg                    request_available
);

    localparam UP   = 1'b0;
    localparam DOWN = 1'b1;

    integer i;
    integer cf;      // signed working copy of current_floor
    reg     found;

    always @(*) begin
        found             = 1'b0;
        request_available = 1'b0;
        target_request    = current_floor;
        cf                = current_floor; // safe signed copy, avoids unsigned wraparound

        if (direction == UP) begin
            // Search upward from current floor first
            for (i = cf; i < NUM_FLOOR; i = i + 1) begin
                if (!found && pending_request[i]) begin
                    target_request     = i[FLOOR_WIDTH-1:0];
                    request_available  = 1'b1;
                    found              = 1'b1;
                end
            end
            // Nothing above -> reverse and search downward
            if (!found) begin
                for (i = cf - 1; i >= 0; i = i - 1) begin
                    if (!found && pending_request[i]) begin
                        target_request    = i[FLOOR_WIDTH-1:0];
                        request_available = 1'b1;
                        found             = 1'b1;
                    end
                end
            end
        end
        else begin // direction == DOWN
            // Search downward from current floor first
            for (i = cf; i >= 0; i = i - 1) begin
                if (!found && pending_request[i]) begin
                    target_request    = i[FLOOR_WIDTH-1:0];
                    request_available = 1'b1;
                    found             = 1'b1;
                end
            end
            // Nothing below -> reverse and search upward
            if (!found) begin
                for (i = cf + 1; i < NUM_FLOOR; i = i + 1) begin
                    if (!found && pending_request[i]) begin
                        target_request    = i[FLOOR_WIDTH-1:0];
                        request_available = 1'b1;
                        found             = 1'b1;
                    end
                end
            end
        end
    end

endmodule

src/floor_5_ele.v
// ============================================================
// Top-level Elevator Controller
// ============================================================
module floor_5_ele #(
    parameter integer NUM_FLOOR   = 5,
    parameter integer FLOOR_WIDTH = $clog2(NUM_FLOOR)
)(
    input  wire                     clk,
    input  wire                     rst,
    input  wire                     emergency,
    input  wire [FLOOR_WIDTH-1:0]   target_floor,

    output reg                      move_up,
    output reg                      move_down,
    output reg                      door_open,

    // Debug/observability outputs (handy for waveform viewing)
    output wire [1:0]               dbg_state,
    output wire [FLOOR_WIDTH-1:0]   dbg_current_floor,
    output wire [NUM_FLOOR-1:0]     dbg_pending_request,
    output wire [FLOOR_WIDTH-1:0]   dbg_target_request,
    output wire                     dbg_request_available,
    output wire                     dbg_direction
);

    reg [1:0] state, next_state;
    reg [FLOOR_WIDTH-1:0] current_floor;
    reg [NUM_FLOOR-1:0]   pending_request;
    reg [2:0]             counter;
    reg                   direction; // 0 = UP, 1 = DOWN

    localparam IDLE       = 2'b00;
    localparam up_state   = 2'b01;
    localparam down_state = 2'b10;
    localparam open_door  = 2'b11;

    localparam MOVE_DELAY = 2;
    localparam DOOR_DELAY = 3;

    wire [FLOOR_WIDTH-1:0] target_request;
    wire                   request_available;

    assign dbg_state              = state;
    assign dbg_current_floor      = current_floor;
    assign dbg_pending_request    = pending_request;
    assign dbg_target_request     = target_request;
    assign dbg_request_available  = request_available;
    assign dbg_direction          = direction;

    scheduler #(
        .NUM_FLOOR   (NUM_FLOOR),
        .FLOOR_WIDTH (FLOOR_WIDTH)
    ) SCH (
        .current_floor     (current_floor),
        .direction         (direction),
        .pending_request   (pending_request),
        .target_request    (target_request),
        .request_available (request_available)
    );

    // ----------------------------------------------------------------
    // Direction latch: remembers which way we were last moving,
    // used by the scheduler to decide search order (SCAN algorithm)
    // ----------------------------------------------------------------
    always @(posedge clk or posedge rst) begin
        if (rst)
            direction <= 1'b0;
        else if (state == up_state)
            direction <= 1'b0;
        else if (state == down_state)
            direction <= 1'b1;
    end

    // ----------------------------------------------------------------
    // Main sequential logic
    // ----------------------------------------------------------------
    always @(posedge clk or posedge rst) begin
        if (rst) begin
            state           <= IDLE;
            current_floor   <= 0;
            pending_request <= {NUM_FLOOR{1'b0}};
            counter         <= 0;
        end
        else if (!emergency) begin
            state <= next_state;

            // --- Request bit management (independent, not mutually exclusive) ---
            if (state == open_door && counter == DOOR_DELAY)
                pending_request[current_floor] <= 1'b0;

            // NOTE: current-floor presses are intentionally allowed here too.
            // If a passenger presses the button for the floor the elevator is
            // already on (while IDLE), this lets the scheduler see it as a
            // valid request and open the door, instead of silently doing
            // nothing forever.
            if (target_floor < NUM_FLOOR)
                pending_request[target_floor] <= 1'b1;

            // --- Movement / counter management ---
            if (state == up_state && target_request != current_floor) begin
                if (counter == MOVE_DELAY) begin
                    counter <= 0;
                    if (current_floor < NUM_FLOOR-1)
                        current_floor <= current_floor + 1'b1;
                end
                else begin
                    counter <= counter + 1'b1;
                end
            end
            else if (state == down_state && target_request != current_floor) begin
                if (counter == MOVE_DELAY) begin
                    counter <= 0;
                    if (current_floor > 0)
                        current_floor <= current_floor - 1'b1;
                end
                else begin
                    counter <= counter + 1'b1;
                end
            end
            else if (state == open_door) begin
                if (counter == DOOR_DELAY)
                    counter <= 0;
                else
                    counter <= counter + 1'b1;
            end
            else begin
                counter <= 0;
            end
        end
    end

    // ----------------------------------------------------------------
    // Next-state logic
    // ----------------------------------------------------------------
    always @(*) begin
        next_state = state;

        case (state)
            IDLE: begin
                if (request_available) begin
                    if (target_request > current_floor)
                        next_state = up_state;
                    else if (target_request < current_floor)
                        next_state = down_state;
                    else
                        next_state = open_door;
                end
            end

            up_state: begin
                if (target_request == current_floor)
                    next_state = open_door;
                else
                    next_state = up_state;
            end

            down_state: begin
                if (target_request == current_floor)
                    next_state = open_door;
                else
                    next_state = down_state;
            end

            open_door: begin
                if (counter == DOOR_DELAY)
                    next_state = IDLE;
                else
                    next_state = open_door;
            end

            default: next_state = IDLE;
        endcase
    end

    // ----------------------------------------------------------------
    // Output logic
    // ----------------------------------------------------------------
    always @(*) begin
        if (emergency) begin
            {move_up, move_down, door_open} = 3'b000;
        end
        else begin
            case (state)
                IDLE:       {move_up, move_down, door_open} = 3'b000;
                up_state:   {move_up, move_down, door_open} = 3'b100;
                down_state: {move_up, move_down, door_open} = 3'b010;
                open_door:  {move_up, move_down, door_open} = 3'b001;
                default:    {move_up, move_down, door_open} = 3'b000;
            endcase
        end
    end

endmodule

testbench/floor_5_ele_tb.v
`timescale 1ns/1ps

module floor_5_ele_tb;

parameter NUM_FLOOR   = 5;
parameter FLOOR_WIDTH = $clog2(NUM_FLOOR);



localparam CLK_PERIOD  = 10;
localparam MOVE_DELAY  = 2;
localparam DOOR_DELAY  = 3;

localparam STEP_TIME   = (MOVE_DELAY + 1) * CLK_PERIOD; // time to move 1 floor  = 30ns
localparam DOOR_TIME   = (DOOR_DELAY + 1) * CLK_PERIOD; // time door stays open = 40ns
localparam MARGIN      = 2 * CLK_PERIOD;                // buffer for state-transition latency = 20ns

reg clk;
reg rst;
reg emergency;
reg [FLOOR_WIDTH-1:0] target_floor;

wire move_up;
wire move_down;
wire door_open;

// Debug outputs
wire [1:0] dbg_state;
wire [FLOOR_WIDTH-1:0] dbg_current_floor;
wire [NUM_FLOOR-1:0] dbg_pending_request;
wire [FLOOR_WIDTH-1:0] dbg_target_request;
wire dbg_request_available;
wire dbg_direction;

//========================================================
// DUT
//========================================================

floor_5_ele DUT(
    .clk(clk),
    .rst(rst),
    .emergency(emergency),
    .target_floor(target_floor),

    .move_up(move_up),
    .move_down(move_down),
    .door_open(door_open),

    .dbg_state(dbg_state),
    .dbg_current_floor(dbg_current_floor),
    .dbg_pending_request(dbg_pending_request),
    .dbg_target_request(dbg_target_request),
    .dbg_request_available(dbg_request_available),
    .dbg_direction(dbg_direction)
);

//========================================================
// Clock
//========================================================

always #(CLK_PERIOD/2) clk = ~clk;

//========================================================
// GTKWave
//========================================================

initial begin
    $dumpfile("dump.vcd");
    $dumpvars(0, floor_5_ele_tb);
end

//========================================================
// Monitor
//========================================================

initial begin
    $monitor("T=%0t | Floor=%0d | Target=%0d | Pending=%b | State=%0d | Dir=%b | UP=%b DOWN=%b DOOR=%b",
             $time,
             dbg_current_floor,
             dbg_target_request,
             dbg_pending_request,
             dbg_state,
             dbg_direction,
             move_up,
             move_down,
             door_open);
end

//========================================================
// Bounds-checked floor request
//
// This is the single place that ever writes to target_floor.
// Any attempt to request a floor outside [0, NUM_FLOOR-1] is
// rejected here and flagged loudly, so an invalid floor code
// (5, 6, or 7 for this 3-bit/5-floor config) can never reach
// the DUT from this testbench, whether by a typo or a copy-paste
// mistake in a test case.
//========================================================
task request_floor(input integer floor);
begin
    if (floor < 0 || floor >= NUM_FLOOR) begin
        $display("  [TB GUARD] Refusing to drive invalid floor %0d (valid range is 0..%0d) at T=%0t",
                  floor, NUM_FLOOR-1, $time);
    end
    else begin
        target_floor = floor[FLOOR_WIDTH-1:0];
    end
end
endtask

//========================================================
// Test Sequence
//========================================================

initial begin

    clk = 0;
    rst = 1;
    emergency = 0;
    target_floor = 0;

    //-------------------------
    // Reset
    //-------------------------
    #(CLK_PERIOD*2);
    rst = 0;

    //-------------------------------------------------
    // Test 1 : Ground -> Floor 4, with two mid-flight
    //          requests added while still moving.
    //          Path: 0 -> 2 (stop) -> 3 (stop) -> 4 (stop)
    //          3 stops, 4 floor-steps total.
    //-------------------------------------------------

    $display("\n========== TEST 1 ==========");
    request_floor(4);

    // add floor 2 after ~1 step of travel
    #(STEP_TIME);
    request_floor(2);

    // add floor 3 after another step
    #(STEP_TIME);
    request_floor(3);

    // remaining time to finish: 4 steps + 3 door stops + margin,
    // minus the 2*STEP_TIME already elapsed above
    #(4*STEP_TIME + 3*DOOR_TIME + MARGIN - 2*STEP_TIME);

    //-------------------------------------------------
    // Test 2 : Go down from floor 4, add a stop at
    //          floor 0 while still descending.
    //          Path: 4 -> 1 (stop) -> 0 (stop)
    //          2 stops, 4 floor-steps total.
    //-------------------------------------------------

    $display("\n========== TEST 2 ==========");
    request_floor(1);

    // request floor 0 partway through the descent
    #(2*STEP_TIME);
    request_floor(0);

    #(4*STEP_TIME + 2*DOOR_TIME + MARGIN - 2*STEP_TIME);

    //-------------------------------------------------
    // Test 3 : Same-floor request - door should open
    //          directly with zero travel steps.
    //-------------------------------------------------

    $display("\n========== TEST 3 ==========");
    request_floor(dbg_current_floor);

    #(DOOR_TIME + MARGIN);

    //-------------------------------------------------
    // Test 4 : Emergency stop mid-travel, then resume.
    //          Path: current -> 4 (2 steps, 1 stop)
    //-------------------------------------------------

    $display("\n========== TEST 4 ==========");
    request_floor(4);

    #(STEP_TIME);
    emergency = 1;

    // hold emergency for a bit, elevator must freeze here
    #(2*CLK_PERIOD);
    emergency = 0;

    #(2*STEP_TIME + DOOR_TIME + MARGIN);

    //-------------------------------------------------
    // Test 5 : Multiple simultaneous-ish requests
    //          (SCAN should reorder them by proximity).
    //          Starting at floor 4, requests: 1, 3, 2
    //          Expected service order going down: nearest first.
    //          Worst case distance: up to 4 steps each way,
    //          3 stops total -> budget generously but not wastefully.
    //-------------------------------------------------

    $display("\n========== TEST 5 ==========");

    request_floor(4);
    #(CLK_PERIOD*2);

    request_floor(1);
    #(CLK_PERIOD*2);

    request_floor(3);
    #(CLK_PERIOD*2);

    request_floor(2);

    #(8*STEP_TIME + 3*DOOR_TIME + MARGIN);

    //-------------------------------------------------
    // Test 6 : Invalid floor codes must be rejected by
    //          the testbench guard itself (5, 6, 7 for
    //          this 3-bit-wide / 5-floor configuration).
    //-------------------------------------------------

    $display("\n========== TEST 6 : invalid floor guard ==========");
    request_floor(5);
    request_floor(6);
    request_floor(7);
    #(4*CLK_PERIOD);

    $display("\n========== SIMULATION COMPLETED at T=%0t ==========", $time);

    $finish;

end

endmodule

dump.vcd
$date
	Sun Jul  5 18:44:08 2026
$end
$version
	Icarus Verilog
$end
$timescale
	1ps
$end
$scope module floor_5_ele_tb $end
$var wire 1 ! move_up $end
$var wire 1 " move_down $end
$var wire 1 # door_open $end
$var wire 3 $ dbg_target_request [2:0] $end
$var wire 2 % dbg_state [1:0] $end
$var wire 1 & dbg_request_available $end
$var wire 5 ' dbg_pending_request [4:0] $end
$var wire 1 ( dbg_direction $end
$var wire 3 ) dbg_current_floor [2:0] $end
$var parameter 32 * CLK_PERIOD $end
$var parameter 32 + DOOR_DELAY $end
$var parameter 65 , DOOR_TIME $end
$var parameter 32 - FLOOR_WIDTH $end
$var parameter 64 . MARGIN $end
$var parameter 32 / MOVE_DELAY $end
$var parameter 32 0 NUM_FLOOR $end
$var parameter 65 1 STEP_TIME $end
$var reg 1 2 clk $end
$var reg 1 3 emergency $end
$var reg 1 4 rst $end
$var reg 3 5 target_floor [2:0] $end
$scope module DUT $end
$var wire 1 2 clk $end
$var wire 3 6 dbg_current_floor [2:0] $end
$var wire 1 ( dbg_direction $end
$var wire 5 7 dbg_pending_request [4:0] $end
$var wire 1 & dbg_request_available $end
$var wire 2 8 dbg_state [1:0] $end
$var wire 3 9 dbg_target_request [2:0] $end
$var wire 1 3 emergency $end
$var wire 1 4 rst $end
$var wire 3 : target_floor [2:0] $end
$var wire 3 ; target_request [2:0] $end
$var wire 1 < request_available $end
$var parameter 32 = DOOR_DELAY $end
$var parameter 32 > FLOOR_WIDTH $end
$var parameter 2 ? IDLE $end
$var parameter 32 @ MOVE_DELAY $end
$var parameter 32 A NUM_FLOOR $end
$var parameter 2 B down_state $end
$var parameter 2 C open_door $end
$var parameter 2 D up_state $end
$var reg 3 E counter [2:0] $end
$var reg 3 F current_floor [2:0] $end
$var reg 1 G direction $end
$var reg 1 # door_open $end
$var reg 1 " move_down $end
$var reg 1 ! move_up $end
$var reg 2 H next_state [1:0] $end
$var reg 5 I pending_request [4:0] $end
$var reg 2 J state [1:0] $end
$scope module SCH $end
$var wire 3 K current_floor [2:0] $end
$var wire 1 G direction $end
$var wire 5 L pending_request [4:0] $end
$var parameter 1 M DOWN $end
$var parameter 32 N FLOOR_WIDTH $end
$var parameter 32 O NUM_FLOOR $end
$var parameter 1 P UP $end
$var reg 1 Q found $end
$var reg 1 < request_available $end
$var reg 3 R target_request [2:0] $end
$var integer 32 S cf [31:0] $end
$var integer 32 T i [31:0] $end
$upscope $end
$upscope $end
$scope task request_floor $end
$var integer 32 U floor [31:0] $end
$upscope $end
$upscope $end
$enddefinitions $end
$comment Show the parameter values. $end
$dumpall
0P
b101 O
b11 N
1M
b1 D
b11 C
b10 B
b101 A
b10 @
b0 ?
b11 >
b11 =
b11110 1
b101 0
b10 /
b10100 .
b11 -
b101000 ,
b11 +
b1010 *
$end
#0
$dumpvars
bx U
b11111111111111111111111111111111 T
b0 S
b0 R
0Q
b0 L
b0 K
b0 J
b0 I
b0 H
0G
b0 F
b0 E
0<
b0 ;
b0 :
b0 9
b0 8
b0 7
b0 6
b0 5
14
03
02
b0 )
0(
b0 '
0&
b0 %
b0 $
0#
0"
0!
$end
#5000
12
#10000
02
#15000
12
#20000
02
b100 5
b100 :
b100 U
04
#25000
b1 H
1Q
1&
1<
b100 $
b100 9
b100 ;
b100 R
b101 T
b10000 '
b10000 7
b10000 I
b10000 L
12
#30000
02
#35000
1!
b1 %
b1 8
b1 J
12
#40000
02
#45000
b1 E
12
#50000
02
b10 5
b10 :
b10 U
#55000
b101 T
b10 $
b10 9
b10 ;
b10 R
1&
1<
1Q
b10 E
b10100 '
b10100 7
b10100 I
b10100 L
12
#60000
02
#65000
b101 T
b1 S
b10 $
b10 9
b10 ;
b10 R
1&
1<
1Q
b1 )
b1 6
b1 F
b1 K
b0 E
12
#70000
02
#75000
b1 E
12
#80000
02
b11 5
b11 :
b11 U
#85000
b101 T
b10 $
b10 9
b10 ;
b10 R
1&
1<
1Q
b10 E
b11100 '
b11100 7
b11100 I
b11100 L
12
#90000
02
#95000
b101 T
b10 S
1&
1<
1Q
b11 H
b10 )
b10 6
b10 F
b10 K
b0 E
12
#100000
02
#105000
0!
1#
b11 %
b11 8
b11 J
12
#110000
02
#115000
b1 E
12
#120000
02
#125000
b10 E
12
#130000
02
#135000
b0 H
b11 E
12
#140000
02
#145000
b11 $
b11 9
b11 ;
b11 R
b101 T
1&
1<
1Q
0#
b1 H
b0 E
b11000 '
b11000 7
b11000 I
b11000 L
b0 %
b0 8
b0 J
12
#150000
02
#155000
1!
b1 %
b1 8
b1 J
12
#160000
02
#165000
b1 E
12
#170000
02
#175000
b10 E
12
#180000
02
#185000
b101 T
b11 S
1&
1<
1Q
b11 H
b11 )
b11 6
b11 F
b11 K
b0 E
12
#190000
02
#195000
0!
1#
b11 %
b11 8
b11 J
12
#200000
02
#205000
b1 E
12
#210000
02
#215000
b10 E
12
#220000
02
#225000
b0 H
b11 E
12
#230000
02
#235000
b101 T
1&
1<
1Q
0#
b11 H
b0 E
b11000 '
b11000 7
b11000 I
b11000 L
b0 %
b0 8
b0 J
12
#240000
02
#245000
1#
b11 %
b11 8
b11 J
12
#250000
02
#255000
b1 E
12
#260000
02
#265000
b10 E
12
#270000
02
#275000
b0 H
b11 E
12
#280000
02
b1 5
b1 :
b1 U
#285000
b100 $
b100 9
b100 ;
b100 R
b101 T
1&
1<
1Q
0#
b1 H
b0 E
b10010 '
b10010 7
b10010 I
b10010 L
b0 %
b0 8
b0 J
12
#290000
02
#295000
1!
b1 %
b1 8
b1 J
12
#300000
02
#305000
b1 E
12
#310000
02
#315000
b10 E
12
#320000
02
#325000
b101 T
b100 S
1&
1<
1Q
b11 H
b100 )
b100 6
b100 F
b100 K
b0 E
12
#330000
02
#335000
0!
1#
b11 %
b11 8
b11 J
12
#340000
02
b0 5
b0 :
b0 U
#345000
b101 T
1&
1<
1Q
b1 E
b10011 '
b10011 7
b10011 I
b10011 L
12
#350000
02
#355000
b10 E
12
#360000
02
#365000
b0 H
b11 E
12
#370000
02
#375000
b1 $
b1 9
b1 ;
b1 R
b11111111111111111111111111111111 T
1&
1<
1Q
0#
b10 H
b0 E
b11 '
b11 7
b11 I
b11 L
b0 %
b0 8
b0 J
12
#380000
02
#385000
1"
b10 %
b10 8
b10 J
12
#390000
02
#395000
b11111111111111111111111111111111 T
b1 $
b1 9
b1 ;
b1 R
1&
1<
1Q
1(
1G
b1 E
12
#400000
02
#405000
b10 E
12
#410000
02
#415000
b11111111111111111111111111111111 T
b11 S
b1 $
b1 9
b1 ;
b1 R
1&
1<
1Q
b11 )
b11 6
b11 F
b11 K
b0 E
12
#420000
02
#425000
b1 E
12
#430000
02
#435000
b10 E
12
#440000
02
#445000
b11111111111111111111111111111111 T
b10 S
b1 $
b1 9
b1 ;
b1 R
1&
1<
1Q
b10 )
b10 6
b10 F
b10 K
b0 E
12
#450000
02
#455000
b1 E
12
#460000
02
#465000
b10 E
12
#470000
02
#475000
b11111111111111111111111111111111 T
b1 S
1&
1<
1Q
b11 H
b1 )
b1 6
b1 F
b1 K
b0 E
12
#480000
02
#485000
0"
1#
b11 %
b11 8
b11 J
12
#490000
02
#495000
b1 E
12
#500000
02
b1 5
b1 :
b1 U
#505000
b10 E
12
#510000
02
#515000
b0 H
b11 E
12
#520000
02
#525000
b11111111111111111111111111111111 T
1&
1<
1Q
0#
b11 H
b0 E
b11 '
b11 7
b11 I
b11 L
b0 %
b0 8
b0 J
12
#530000
02
#535000
1#
b11 %
b11 8
b11 J
12
#540000
02
#545000
b1 E
12
#550000
02
#555000
b10 E
12
#560000
02
b100 5
b100 :
b100 U
#565000
b0 H
b11111111111111111111111111111111 T
1&
1<
1Q
b11 E
b10011 '
b10011 7
b10011 I
b10011 L
12
#570000
02
#575000
b0 $
b0 9
b0 ;
b0 R
b11111111111111111111111111111111 T
1&
1<
1Q
0#
b10 H
b0 E
b10001 '
b10001 7
b10001 I
b10001 L
b0 %
b0 8
b0 J
12
#580000
02
#585000
1"
b10 %
b10 8
b10 J
12
#590000
0"
02
13
#595000
12
#600000
02
#605000
12
#610000
1"
02
03
#615000
b1 E
12
#620000
02
#625000
b10 E
12
#630000
02
#635000
b11111111111111111111111111111111 T
b0 S
1&
1<
1Q
b11 H
b0 )
b0 6
b0 F
b0 K
b0 E
12
#640000
02
#645000
0"
1#
b11 %
b11 8
b11 J
12
#650000
02
#655000
b1 E
12
#660000
02
#665000
b10 E
12
#670000
02
#675000
b0 H
b11 E
12
#680000
02
#685000
b100 $
b100 9
b100 ;
b100 R
b101 T
1&
1<
1Q
0#
b1 H
b0 E
b10000 '
b10000 7
b10000 I
b10000 L
b0 %
b0 8
b0 J
12
#690000
02
#695000
1!
b1 %
b1 8
b1 J
12
#700000
02
#705000
b101 T
b100 $
b100 9
b100 ;
b100 R
1&
1<
1Q
b1 E
0(
0G
12
#710000
02
#715000
b10 E
12
#720000
02
#725000
b101 T
b1 S
b100 $
b100 9
b100 ;
b100 R
1&
1<
1Q
b1 )
b1 6
b1 F
b1 K
b0 E
12
#730000
02
#735000
b1 E
12
#740000
02
#745000
b10 E
12
#750000
02
b1 5
b1 :
b1 U
#755000
b101 T
b10 S
b100 $
b100 9
b100 ;
b100 R
1&
1<
1Q
b10 )
b10 6
b10 F
b10 K
b0 E
b10010 '
b10010 7
b10010 I
b10010 L
12
#760000
02
#765000
b1 E
12
#770000
02
b11 5
b11 :
b11 U
#775000
b101 T
b11 $
b11 9
b11 ;
b11 R
1&
1<
1Q
b10 E
b11010 '
b11010 7
b11010 I
b11010 L
12
#780000
02
#785000
b101 T
b11 S
1&
1<
1Q
b11 H
b11 )
b11 6
b11 F
b11 K
b0 E
12
#790000
02
b10 5
b10 :
b10 U
#795000
b101 T
1&
1<
1Q
0!
1#
b11110 '
b11110 7
b11110 I
b11110 L
b11 %
b11 8
b11 J
12
#800000
02
#805000
b1 E
12
#810000
02
#815000
b10 E
12
#820000
02
#825000
b0 H
b11 E
12
#830000
02
#835000
b100 $
b100 9
b100 ;
b100 R
b101 T
1&
1<
1Q
0#
b1 H
b0 E
b10110 '
b10110 7
b10110 I
b10110 L
b0 %
b0 8
b0 J
12
#840000
02
#845000
1!
b1 %
b1 8
b1 J
12
#850000
02
#855000
b1 E
12
#860000
02
#865000
b10 E
12
#870000
02
#875000
b101 T
b100 S
1&
1<
1Q
b11 H
b100 )
b100 6
b100 F
b100 K
b0 E
12
#880000
02
#885000
0!
1#
b11 %
b11 8
b11 J
12
#890000
02
#895000
b1 E
12
#900000
02
#905000
b10 E
12
#910000
02
#915000
b0 H
b11 E
12
#920000
02
#925000
b10 $
b10 9
b10 ;
b10 R
b11111111111111111111111111111111 T
1&
1<
1Q
0#
b10 H
b0 E
b110 '
b110 7
b110 I
b110 L
b0 %
b0 8
b0 J
12
#930000
02
#935000
1"
b10 %
b10 8
b10 J
12
#940000
02
#945000
b11111111111111111111111111111111 T
b10 $
b10 9
b10 ;
b10 R
1&
1<
1Q
b1 E
1(
1G
12
#950000
02
#955000
b10 E
12
#960000
02
#965000
b11111111111111111111111111111111 T
b11 S
b10 $
b10 9
b10 ;
b10 R
1&
1<
1Q
b11 )
b11 6
b11 F
b11 K
b0 E
12
#970000
02
#975000
b1 E
12
#980000
02
#985000
b10 E
12
#990000
02
#995000
b11111111111111111111111111111111 T
b10 S
1&
1<
1Q
b11 H
b10 )
b10 6
b10 F
b10 K
b0 E
12
#1000000
02
#1005000
0"
1#
b11 %
b11 8
b11 J
12
#1010000
02
#1015000
b1 E
12
#1020000
02
#1025000
b10 E
12
#1030000
02
#1035000
b0 H
b11 E
12
#1040000
02
#1045000
b11111111111111111111111111111111 T
1&
1<
1Q
0#
b11 H
b0 E
b110 '
b110 7
b110 I
b110 L
b0 %
b0 8
b0 J
12
#1050000
02
#1055000
1#
b11 %
b11 8
b11 J
12
#1060000
02
#1065000
b1 E
12
#1070000
02
#1075000
b10 E
12
#1080000
02
#1085000
b0 H
b11 E
12
#1090000
02
#1095000
b11111111111111111111111111111111 T
1&
1<
1Q
0#
b11 H
b0 E
b110 '
b110 7
b110 I
b110 L
b0 %
b0 8
b0 J
12
#1100000
02
#1105000
1#
b11 %
b11 8
b11 J
12
#1110000
02
#1115000
b1 E
12
#1120000
02
#1125000
b10 E
12
#1130000
02
#1135000
b0 H
b11 E
12
#1140000
02
#1145000
b11111111111111111111111111111111 T
1&
1<
1Q
0#
b11 H
b0 E
b110 '
b110 7
b110 I
b110 L
b0 %
b0 8
b0 J
12
#1150000
02
#1155000
1#
b11 %
b11 8
b11 J
12
#1160000
02
#1165000
b1 E
12
#1170000
02
b111 U
#1175000
b10 E
12
#1180000
02
#1185000
b0 H
b11 E
12
#1190000
02
#1195000
b11111111111111111111111111111111 T
1&
1<
1Q
0#
b11 H
b0 E
b110 '
b110 7
b110 I
b110 L
b0 %
b0 8
b0 J
12
#1200000
02
#1205000
1#
b11 %
b11 8
b11 J
12
